{
    "minmax": {
        "number_of_evaluations": {
            "0.5": 83965518,
            "1.0": 92643423,
            "1.5": 99781721,
            "2.0": 69418150,
            "total": 345808812
        },
        "number_of_games": {
            "0.5": 485,
            "1.0": 593,
            "1.5": 411,
            "2.0": 151,
            "total": 1640
        },
        "timeouts": {
            "0.5": 10316,
            "1.0": 5985,
            "1.5": 2628,
            "2.0": 1465,
            "total": 20394
        },
        "turns_played": {
            "0.5": 11247,
            "1.0": 7960,
            "1.5": 6424,
            "2.0": 3634,
            "total": 29265
        }
    },
    "pruning": {
        "number_of_evaluations": {
            "0.5": 52083947,
            "1.0": 94716756,
            "1.5": 64353768,
            "2.0": 8564825,
            "total": 219719296
        },
        "number_of_games": {
            "0.5": 485,
            "1.0": 593,
            "1.5": 411,
            "2.0": 151,
            "total": 1640
        },
        "timeouts": {
            "0.5": 6705,
            "1.0": 2048,
            "1.5": 523,
            "2.0": 262,
            "total": 9538
        },
        "turns_played": {
            "0.5": 10071,
            "1.0": 15319,
            "1.5": 9494,
            "2.0": 1348,
            "total": 36232
        }
    },
    "random": {
        "number_of_evaluations": {
            "0.5": 0,
            "1.0": 0,
            "1.5": 0,
            "2.0": 0,
            "total": 0
        },
        "number_of_games": {
            "0.5": 485,
            "1.0": 593,
            "1.5": 411,
            "2.0": 151,
            "total": 1640
        },
        "timeouts": {
            "0.5": 0,
            "1.0": 0,
            "1.5": 0,
            "2.0": 0,
            "total": 0
        },
        "turns_played": {
            "0.5": 6205,
            "1.0": 2040,
            "1.5": 2919,
            "2.0": 610,
            "total": 11774
        }
    }
}